puts/__init__.py
puts/_color.py
puts/_encoding.py
puts/_file.py
puts/_logging.py
puts/_string.py
puts/_time.py
puts/_utils.py
puts/logger.py
puts-0.0.11.dist-info/LICENSE
puts-0.0.11.dist-info/METADATA
puts-0.0.11.dist-info/WHEEL
puts-0.0.11.dist-info/top_level.txt
puts-0.0.11.dist-info/RECORD
